BasisConvolution/convLayerv2.py
BasisConvolution/convLayerv3.py
BasisConvolution/convNetv2.py
BasisConvolution/convNetv3.py
BasisConvolution/data.py
BasisConvolution/detail/DataLoader.py
BasisConvolution/detail/activation.py
BasisConvolution/detail/augment.py
BasisConvolution/detail/basis.py
BasisConvolution/detail/cutlass.py
BasisConvolution/detail/cutlassv2.py
BasisConvolution/detail/dataloader.py
BasisConvolution/detail/dataset.py
BasisConvolution/detail/initialization.py
BasisConvolution/detail/mapping.py
BasisConvolution/detail/mlp.py
BasisConvolution/detail/radius.py
BasisConvolution/detail/scatter.py
BasisConvolution/detail/typing.py
BasisConvolution/detail/util.py
BasisConvolution/detail/windows.py
BasisConvolution/neighborhoodFallback/naive.py
BasisConvolution/neighborhoodFallback/neighborhood.py
BasisConvolution/neighborhoodFallback/util.py
BasisConvolution/sph/kernels.py
BasisConvolution/sph/neighborhood.py
BasisConvolution/sph/sphOps.py
BasisConvolution/sph/kernelFunctions/AdhesionKernel.py
BasisConvolution/sph/kernelFunctions/CohesionKernel.py
BasisConvolution/sph/kernelFunctions/CubicSpline.py
BasisConvolution/sph/kernelFunctions/Poly6.py
BasisConvolution/sph/kernelFunctions/QuarticSpline.py
BasisConvolution/sph/kernelFunctions/QuinticSpline.py
BasisConvolution/sph/kernelFunctions/Spiky.py
BasisConvolution/sph/kernelFunctions/ViscosityKernel.py
BasisConvolution/sph/kernelFunctions/Wendland2.py
BasisConvolution/sph/kernelFunctions/Wendland4.py
BasisConvolution/sph/kernelFunctions/Wendland6.py
BasisConvolution/test_case_I/train.py
BasisConvolution/util/arguments.py
BasisConvolution/util/augment.py
BasisConvolution/util/dataPlotting.py
BasisConvolution/util/dataloader.py
BasisConvolution/util/datautils.py
BasisConvolution/util/features.py
BasisConvolution/util/hyperparameters.py
BasisConvolution/util/network.py
BasisConvolution/util/plotting.py
BasisConvolution/util/radius.py
BasisConvolution/util/testcases.py
basisconvolution-0.2.1.dist-info/licenses/LICENSE
basisconvolution-0.2.1.dist-info/METADATA
basisconvolution-0.2.1.dist-info/WHEEL
basisconvolution-0.2.1.dist-info/top_level.txt
basisconvolution-0.2.1.dist-info/RECORD
