Metadata-Version: 2.4
Name: BasisConvolution
Version: 0.2.1
Summary: Graph Neural Network Library for continuous convolutions using separable basis functions in pyTorch.
Author-email: Rene Winchenbach <contact@fluids.dev>
Maintainer-email: Rene Winchenbach <contact@fluids.dev>
License: MIT License
Project-URL: Repository, https://github.com/tum-pbs/SFBC
Project-URL: Issues, https://github.com/tum-pbs/SFBC/issues
Keywords: sph,machineLearning,pytorch,GNN
Classifier: Development Status :: 4 - Beta
Classifier: Intended Audience :: Developers
Classifier: Programming Language :: Python :: 3
Classifier: License :: OSI Approved :: MIT License
Classifier: Operating System :: OS Independent
Requires-Python: >=3.10
License-File: LICENSE
Requires-Dist: torch
Requires-Dist: numpy
Requires-Dist: ninja
Requires-Dist: tqdm
Requires-Dist: seaborn
Requires-Dist: pandas
Requires-Dist: matplotlib
Requires-Dist: tomli
Requires-Dist: msgpack
Requires-Dist: msgpack-numpy
Requires-Dist: portalocker
Requires-Dist: h5py
Requires-Dist: zstandard
Requires-Dist: scipy
Requires-Dist: scikit-learn
Requires-Dist: scikit-image
Requires-Dist: numba
Dynamic: license-file
